README.rst
setup.py
tensorlab/__init__.py
tensorlab/tensorlab.py
tensorlab.egg-info/PKG-INFO
tensorlab.egg-info/SOURCES.txt
tensorlab.egg-info/dependency_links.txt
tensorlab.egg-info/not-zip-safe
tensorlab.egg-info/requires.txt
tensorlab.egg-info/top_level.txt